README
setup.py
Nestache.egg-info/PKG-INFO
Nestache.egg-info/SOURCES.txt
Nestache.egg-info/dependency_links.txt
Nestache.egg-info/not-zip-safe
Nestache.egg-info/requires.txt
Nestache.egg-info/top_level.txt
nestache/__init__.py
nestache/nestview.py