Metadata-Version: 1.0
Name: Nestache
Version: 0.4.0
Summary: Nested View for Mustache
Home-page: http://github.com/ahri/nestache
Author: Adam Piper
Author-email: adam@ahri.net
License: AGPLv3
Platform: any
Classifier: Development Status :: 4 - Beta
Classifier: Environment :: Web Environment
Classifier: Intended Audience :: Developers
Classifier: License :: OSI Approved :: GNU Affero General Public License v3
Classifier: Operating System :: OS Independent
Classifier: Programming Language :: Python
Classifier: Topic :: Internet :: WWW/HTTP :: Dynamic Content
Classifier: Topic :: Software Development :: Libraries :: Python Modules
